{
  "generated_at": "2025-11-28T10:20:29.074710",
  "benchmark_comparison": {
    "period_days": 90,
    "benchmark": {
      "symbol": "SPY",
      "return_pct": 7.17,
      "volatility_pct": 11.85,
      "sharpe": 0.51
    },
    "portfolio": {
      "return_pct": 0.8,
      "volatility_pct": 5.35,
      "sharpe": -0.06,
      "positions": 25
    },
    "comparison": {
      "alpha_pct": -6.37,
      "outperformance": "False",
      "sharpe_diff": -0.57
    }
  },
  "turnover": {
    "turnover_pct": 5.83,
    "entries": [
      "INTU"
    ],
    "exits": [
      "MDB"
    ],
    "entries_count": 1,
    "exits_count": 1,
    "unchanged_count": 24
  },
  "portfolio_history": [
    {
      "date": "2025-11-26",
      "positions": 25,
      "perf_3m": 2.01
    },
    {
      "date": "2025-11-27",
      "positions": 25,
      "perf_3m": 1.34
    },
    {
      "date": "2025-11-28",
      "positions": 25,
      "perf_3m": 0.8
    }
  ]
}